lasso/__init__.py
lasso/releasers/VERSION.txt
lasso/releasers/__init__.py
lasso/releasers/_python_version.py
lasso/releasers/maven_release.py
lasso/releasers/nodejs_release.py
lasso/releasers/python_release.py
lasso/releasers/release.py
lasso_releasers-2.0.0.dist-info/licenses/LICENSE.md
lasso_releasers-2.0.0.dist-info/licenses/NOTICE.txt
lasso_releasers-2.0.0.dist-info/METADATA
lasso_releasers-2.0.0.dist-info/WHEEL
lasso_releasers-2.0.0.dist-info/entry_points.txt
lasso_releasers-2.0.0.dist-info/top_level.txt
lasso_releasers-2.0.0.dist-info/zip-safe
lasso_releasers-2.0.0.dist-info/RECORD
