Metadata-Version: 2.4
Name: lasso.releasers
Version: 2.0.0
Summary: Release artifact publication automation for the Planetary Data System
Home-page: https://github.com/NASA-PDS/lasso-releasers
Download-URL: https://github.com/NASA-PDS/lasso-releasers/releases/
Author: PDS
Author-email: pds_operator@jpl.nasa.gov
License: apache-2.0
Keywords: pds,planetary data,ci,automation,release
Classifier: Programming Language :: Python :: 3
Classifier: Programming Language :: Python :: 3.13
Classifier: Operating System :: OS Independent
Requires-Python: >=3.13
License-File: LICENSE.md
License-File: NOTICE.txt
Requires-Dist: github3.py==4.0.1
Requires-Dist: lxml==6.0.0
Requires-Dist: packaging~=25.0
Provides-Extra: dev
Requires-Dist: black; extra == "dev"
Requires-Dist: flake8; extra == "dev"
Requires-Dist: flake8-bugbear; extra == "dev"
Requires-Dist: flake8-docstrings; extra == "dev"
Requires-Dist: pep8-naming; extra == "dev"
Requires-Dist: mypy; extra == "dev"
Requires-Dist: pydocstyle; extra == "dev"
Requires-Dist: coverage; extra == "dev"
Requires-Dist: pytest; extra == "dev"
Requires-Dist: pytest-cov; extra == "dev"
Requires-Dist: pytest-watch; extra == "dev"
Requires-Dist: pytest-xdist; extra == "dev"
Requires-Dist: pre-commit; extra == "dev"
Requires-Dist: sphinx; extra == "dev"
Requires-Dist: sphinx-rtd-theme; extra == "dev"
Requires-Dist: tox; extra == "dev"
Requires-Dist: types-setuptools; extra == "dev"
Dynamic: download-url
Dynamic: license-file
